odoo10_addon_attribute_set_searchable-10.0.1.0.0.99.dev6-py3.8-nspkg.pth
odoo/addons/attribute_set_searchable/README.rst
odoo/addons/attribute_set_searchable/__init__.py
odoo/addons/attribute_set_searchable/__manifest__.py
odoo/addons/attribute_set_searchable/models/__init__.py
odoo/addons/attribute_set_searchable/models/attribute_attribute.py
odoo/addons/attribute_set_searchable/models/ir_ui_custom_field_filter.py
odoo/addons/attribute_set_searchable/readme/CONTRIBUTORS.rst
odoo/addons/attribute_set_searchable/readme/DESCRIPTION.rst
odoo/addons/attribute_set_searchable/readme/USAGE.rst
odoo/addons/attribute_set_searchable/static/description/icon.png
odoo/addons/attribute_set_searchable/static/description/index.html
odoo/addons/attribute_set_searchable/tests/__init__.py
odoo/addons/attribute_set_searchable/tests/test_attribute_set_searchable.py
odoo/addons/attribute_set_searchable/views/attribute_attribute.xml
odoo10_addon_attribute_set_searchable-10.0.1.0.0.99.dev6.dist-info/METADATA
odoo10_addon_attribute_set_searchable-10.0.1.0.0.99.dev6.dist-info/WHEEL
odoo10_addon_attribute_set_searchable-10.0.1.0.0.99.dev6.dist-info/namespace_packages.txt
odoo10_addon_attribute_set_searchable-10.0.1.0.0.99.dev6.dist-info/top_level.txt
odoo10_addon_attribute_set_searchable-10.0.1.0.0.99.dev6.dist-info/RECORD
